BioSANS2020/BioSANS.py
BioSANS2020/BioSSL.py
BioSANS2020/RunBioSANS.py
BioSANS2020/__init__.py
BioSANS2020/__main__.py
BioSANS2020/biosans_lib.py
BioSANS2020/analysis/__init__.py
BioSANS2020/analysis/numeric/__init__.py
BioSANS2020/analysis/numeric/sample_points.py
BioSANS2020/analysis/numeric/transform_data.py
BioSANS2020/analysis/plotting/__init__.py
BioSANS2020/analysis/plotting/plot_traj.py
BioSANS2020/cli_functs/__init__.py
BioSANS2020/cli_functs/ssl_calls.py
BioSANS2020/gui_functs/__init__.py
BioSANS2020/gui_functs/draw_figure.py
BioSANS2020/gui_functs/prepare_canvas.py
BioSANS2020/gui_functs/scrollable_text.py
BioSANS2020/math_functs/__init__.py
BioSANS2020/math_functs/sbml_math.py
BioSANS2020/model/__init__.py
BioSANS2020/model/new_file.py
BioSANS2020/model/topology_view.py
BioSANS2020/model/fileconvert/__init__.py
BioSANS2020/model/fileconvert/convtopotosbml.py
BioSANS2020/model/fileconvert/process_sbml.py
BioSANS2020/model/ode_parse/__init__.py
BioSANS2020/model/ode_parse/ode_extract.py
BioSANS2020/model/param_est/__init__.py
BioSANS2020/model/param_est/my_mcem.py
BioSANS2020/model/param_est/param_estimate.py
BioSANS2020/model/param_est/param_slider.py
BioSANS2020/myglobal/__init__.py
BioSANS2020/myglobal/mglobals.py
BioSANS2020/myglobal/proc_global.py
BioSANS2020/prepcodes/__init__.py
BioSANS2020/prepcodes/get_topo_data.py
BioSANS2020/prepcodes/process.py
BioSANS2020/prepcodes/processes_hub.py
BioSANS2020/propagation/__init__.py
BioSANS2020/propagation/create_wxmaxima_command.py
BioSANS2020/propagation/law_of_localization.py
BioSANS2020/propagation/propensity.py
BioSANS2020/propagation/recalculate_globals.py
BioSANS2020/propagation/deterministic/__init__.py
BioSANS2020/propagation/deterministic/euler_mod.py
BioSANS2020/propagation/deterministic/lna_approx.py
BioSANS2020/propagation/deterministic/lna_function_of_time.py
BioSANS2020/propagation/deterministic/ode_int.py
BioSANS2020/propagation/deterministic/runge_kutta4.py
BioSANS2020-0.3.2.dist-info/LICENSE
BioSANS2020-0.3.2.dist-info/METADATA
BioSANS2020-0.3.2.dist-info/WHEEL
BioSANS2020-0.3.2.dist-info/entry_points.txt
BioSANS2020-0.3.2.dist-info/top_level.txt
BioSANS2020-0.3.2.dist-info/RECORD
