Metadata-Version: 2.1
Name: BioSANS2020
Version: 0.3.2
Summary: Symbolic and Numeric Software for Systems Biology
Home-page: https://efajiculay.github.io/SysBioSoft/
Author: Erickson Erigio Fajiculay
Author-email: efajiculay@yahoo.com
License: GPLv3
Platform: UNKNOWN
Classifier: Development Status :: 5 - Production/Stable
Classifier: Programming Language :: Python :: 3
Classifier: License :: OSI Approved :: GNU General Public License v3 (GPLv3)
Classifier: Operating System :: OS Independent
Classifier: Topic :: Scientific/Engineering :: Bio-Informatics
Requires-Python: >=3.7
License-File: LICENSE
Requires-Dist: DateTime
Requires-Dist: pathlib
Requires-Dist: Pillow
Requires-Dist: numpy
Requires-Dist: thread6
Requires-Dist: pandas
Requires-Dist: matplotlib (==3.3.3)
Requires-Dist: python-libsbml
Requires-Dist: scipy
Requires-Dist: func-timeout
Requires-Dist: sympy
Requires-Dist: applescript
